tddpy/__init__.py
tddpy/abstract_coordinator.py
tddpy/ctdd.pyd
tddpy/ctdd.so
tddpy/global_method.py
tddpy/global_order_coordinator.py
tddpy/node.py
tddpy/tdd.py
tddpy/trival_coordinator.py
tddpy/CUDAcpl/CUDAcpl_Tensor.py
tddpy/CUDAcpl/__init__.py
tddpy/CUDAcpl/config.py
tddpy/CUDAcpl/main.py
tddpy/CUDAcpl/quantum_circ.py
TddPy-1.0b31.dist-info/LICENSE
TddPy-1.0b31.dist-info/METADATA
TddPy-1.0b31.dist-info/WHEEL
TddPy-1.0b31.dist-info/top_level.txt
TddPy-1.0b31.dist-info/RECORD
